perekrestok_api/__init__.py
perekrestok_api/abstraction.py
perekrestok_api/manager.py
perekrestok_api/endpoints/__init__.py
perekrestok_api/endpoints/advertising.py
perekrestok_api/endpoints/catalog.py
perekrestok_api/endpoints/general.py
perekrestok_api/endpoints/geolocation.py
perekrestok_api-0.1.8.dist-info/licenses/LICENSE
perekrestok_api-0.1.8.dist-info/METADATA
perekrestok_api-0.1.8.dist-info/WHEEL
perekrestok_api-0.1.8.dist-info/top_level.txt
perekrestok_api-0.1.8.dist-info/RECORD
