Metadata-Version: 2.4
Name: perekrestok_api
Version: 0.1.8
Summary: A Python API client for Perekrestok catalog
Author: Miskler
License-Expression: MIT
Project-URL: Homepage, https://github.com/Open-Inflation/perekrestok_api
Project-URL: Repository, https://github.com/Open-Inflation/perekrestok_api
Project-URL: Documentation, https://open-inflation.github.io/perekrestok_api/quick_start
Keywords: api,perekrestok,store,catalog
Classifier: Programming Language :: Python :: 3
Classifier: Programming Language :: Python :: 3.10
Classifier: Programming Language :: Python :: 3.11
Classifier: Programming Language :: Python :: 3.12
Classifier: Programming Language :: Python :: 3.13
Classifier: Operating System :: Microsoft :: Windows
Classifier: Operating System :: POSIX :: Linux
Classifier: Intended Audience :: Developers
Classifier: Intended Audience :: Information Technology
Classifier: Topic :: Software Development :: Libraries :: Python Modules
Classifier: Topic :: Internet
Classifier: Topic :: Utilities
Requires-Python: >=3.10
License-File: LICENSE
Requires-Dist: hrequests[all]
Requires-Dist: requests
Provides-Extra: tests
Requires-Dist: pytest; extra == "tests"
Requires-Dist: pytest-asyncio; extra == "tests"
Requires-Dist: pytest-jsonschema-snapshot; extra == "tests"
Requires-Dist: jsoncrack-for-sphinx; extra == "tests"
Requires-Dist: furo; extra == "tests"
Dynamic: license-file
